README.md
pyproject.toml
setup.cfg
setup.py
pnguin/__init__.py
pnguin.egg-info/PKG-INFO
pnguin.egg-info/SOURCES.txt
pnguin.egg-info/dependency_links.txt
pnguin.egg-info/requires.txt
pnguin.egg-info/top_level.txt