Metadata-Version: 2.1
Name: pnguin
Version: 0.0.1
Summary: A simple, dual-axis DataFrame library with remote support
Home-page: https://github.com/raghavmecheri/pnguin
Author: Raghav Mecheri
Author-email: raghav.mecheri@columia.edu
License: MIT
Download-URL: https://github.com/raghavmecheri/pnguin/archive/0.0.1.zip
Platform: UNKNOWN
Classifier: Development Status :: 3 - Alpha
Classifier: Intended Audience :: Science/Research
Classifier: License :: OSI Approved :: MIT License
Classifier: Operating System :: POSIX :: Linux
Classifier: Operating System :: MacOS :: MacOS X
Classifier: Operating System :: Microsoft :: Windows :: Windows 10
Classifier: Programming Language :: Python :: 3.7
